demo/__init__.py
demo/data.dat
demo/mod_a.py
demo/data/data.txt
demo/p_x/__init__.py
py_pkg_demo/__init__.py
py_pkg_demo/mod_a.py
py_pkg_demo/p_x/__init__.py
python_packaging_demo-0.1.7.data/data/py_pkg_demo_data/data.txt
python_packaging_demo-0.1.7.dist-info/DESCRIPTION.rst
python_packaging_demo-0.1.7.dist-info/entry_points.txt
python_packaging_demo-0.1.7.dist-info/METADATA
python_packaging_demo-0.1.7.dist-info/metadata.json
python_packaging_demo-0.1.7.dist-info/RECORD
python_packaging_demo-0.1.7.dist-info/top_level.txt
python_packaging_demo-0.1.7.dist-info/WHEEL
